Compiled from "Main.java"
public class JDBCExample.Main {
  static final java.lang.String JDBC_DRIVER;

  static final java.lang.String DB_URL;

  static final java.lang.String USER;

  static final java.lang.String PASS;

  public JDBCExample.Main();
    Code:
       0: aload_0
       1: invokespecial #1                  // Method java/lang/Object."<init>":()V
       4: return

  public static void main(java.lang.String[]);
    Code:
       0: iconst_2
       1: anewarray     #2                  // class java/lang/Object
       4: dup
       5: iconst_0
       6: iconst_1
       7: invokestatic  #3                  // Method java/lang/Integer.valueOf:(I)Ljava/lang/Integer;
      10: aastore
      11: dup
      12: iconst_1
      13: ldc           #4                  // String abc
      15: aastore
      16: invokestatic  #5                  // Method genCodeTest:([Ljava/lang/Object;)V
      19: return

  static void genCodeTest(java.lang.Object...);
    Code:
       0: return
}
